edwh_devdb_plugin/__about__.py
edwh_devdb_plugin/__init__.py
edwh_devdb_plugin/devdb_plugin.py
edwh_devdb_plugin-0.6.3.dist-info/METADATA
edwh_devdb_plugin-0.6.3.dist-info/WHEEL
edwh_devdb_plugin-0.6.3.dist-info/entry_points.txt
edwh_devdb_plugin-0.6.3.dist-info/licenses/LICENSE.txt
edwh_devdb_plugin-0.6.3.dist-info/RECORD
